{
  "schema": [
    {
      "name": "label",
      "type": 9
    },
    {
      "name": "style",
      "type": 2
    },
    {
      "name": "name",
      "type": 7
    }
  ],
  "rows": [
    {
      "$id": 1,
      "label": "tev026601_JNK0010",
      "style": 4,
      "name": "질문"
    },
    {
      "$id": 2,
      "label": "tev026601_SEL0011",
      "style": 3,
      "name": "돌에 관해 묻는다"
    },
    {
      "$id": 3,
      "label": "tev026601_JNK0020",
      "style": 4,
      "name": "흥미"
    },
    {
      "$id": 4,
      "label": "tev026601_SEL0021",
      "style": 3,
      "name": "최근 상황을 묻는다"
    },
    {
      "$id": 5,
      "label": "tev026601_SEL0041",
      "style": 3,
      "name": "돌 라이선스에 관해 묻는다[ST:wait ]"
    },
    {
      "$id": 6,
      "label": "tev026601_SEL0051",
      "style": 3,
      "name": "돌 관리 방법을 묻는다[ST:wait ]"
    },
    {
      "$id": 7,
      "label": "tev026601_SEL0061",
      "style": 3,
      "name": "돌 비행 형태에 관해 묻는다"
    },
    {
      "$id": 8,
      "label": "tev026601_SEL0071",
      "style": 3,
      "name": "울프에 관해 묻는다"
    },
    {
      "$id": 9,
      "label": "tev026601_MSG0001",
      "style": 1,
      "name": "돌에 타고 싶나요?\n……돌을 사랑하는 마음\n멋져요![ST:wait ]"
    },
    {
      "$id": 10,
      "label": "tev026601_MSG0002",
      "style": 1,
      "name": "블레이드로서 실력을 인정받으면\n당신에게도 돌을 가질 자격이\n주어질 거라고 생각해요[ST:wait ]"
    },
    {
      "$id": 11,
      "label": "tev026601_MSG0003",
      "style": 1,
      "name": "그때까지는 힘들겠지만\n자신의 다리로 미라를 걸어 다녀 주세요[ST:wait ]"
    },
    {
      "$id": 12,
      "label": "tev026601_MSG0004",
      "style": 1,
      "name": "맞다, 전투에서 모르는 것이 있으면\n울프 씨에게 물어보면 돼요![ST:wait ]"
    },
    {
      "$id": 13,
      "label": "tev026601_MSG0005",
      "style": 1,
      "name": "호랑이 교관이라고 불리고 있으니\n물어볼 때는 모쪼록 주의해 주세요[ST:wait ]"
    },
    {
      "$id": 14,
      "label": "tev026601_MSG0008",
      "style": 1,
      "name": "메츠 씨에게 물자를 전해 주셨군요![ST:wait ]"
    },
    {
      "$id": 15,
      "label": "tev026601_MSG0009",
      "style": 1,
      "name": "메츠 씨가 좋은 블레이드를 보내 줘서\n고맙다고 연락해 왔어요[ST:wait ]"
    },
    {
      "$id": 16,
      "label": "tev026601_MSG0010",
      "style": 1,
      "name": "본인은 [ST:playername ]보다\n더 많은 무용담을 만들겠다면서\n서둘러 임무를 수행하러 가 버렸어요……[ST:wait ]"
    },
    {
      "$id": 17,
      "label": "tev026601_MSG0011",
      "style": 1,
      "name": "메츠 씨의 돌이 걱정이에요\n조심히 좀 싸워 주면 좋겠는데……\n메츠 씨가 조종을 거칠게 해서……[ST:wait ]"
    },
    {
      "$id": 18,
      "label": "tev026601_MSG0012",
      "style": 1,
      "name": "저처럼 돌을 사랑하는\n크리스토퍼 씨의 발뒤꿈치만큼이라도\n소중히 대해 줬으면……[ST:wait ]"
    },
    {
      "$id": 19,
      "label": "tev026601_MSG0020",
      "style": 1,
      "name": "흠…… 흠흠…… 합격!\n사적으로 합격![ST:wait ]"
    },
    {
      "$id": 20,
      "label": "tev026601_MSG0021",
      "style": 1,
      "name": "당신이라면 돌을 맡겨도\n괜찮을 것 같은 기분이 들어요![ST:wait ]"
    },
    {
      "$id": 21,
      "label": "tev026601_MSG0022",
      "style": 1,
      "name": "호랑이 교관인 울프 씨도\n보증해 줄 거예요![ST:wait ]"
    },
    {
      "$id": 22,
      "label": "tev026601_MSG0023",
      "style": 1,
      "name": "돌 라이선스 취득에 관해\n반담 사령관님에게 물어봐 주세요[ST:wait ]"
    },
    {
      "$id": 23,
      "label": "tev026601_MSG0024",
      "style": 1,
      "name": "사령관님은 당신을 시험하고 싶어서\n블레이드 홈에서\n근질근질해하고 있지 않을까요?[ST:wait ]"
    },
    {
      "$id": 24,
      "label": "tev026601_MSG0030",
      "style": 1,
      "name": "언젠가 돌 라이선스를 따고 싶어서\n다양한 블레이드 사람에게 물어보며\n시험 내용을 예습 중이에요![ST:wait ]"
    },
    {
      "$id": 25,
      "label": "tev026601_MSG0031",
      "style": 1,
      "name": "예를 들면 컬렉피디언의 시험에서 필요한\n아르나지크는 야광의 숲에서 채취할 수 있어요![ST:wait ]"
    },
    {
      "$id": 26,
      "label": "tev026601_MSG0032",
      "style": 1,
      "name": "그리고 기 도우 호박은 망각의 계곡의\n바젤 호수 근처에서 찾을 수 있다고 해요!\n상당히 희귀하다는 것 같지만요[ST:wait ]"
    },
    {
      "$id": 27,
      "label": "tev026601_MSG0033",
      "style": 1,
      "name": ""
    },
    {
      "$id": 28,
      "label": "tev026601_MSG0034",
      "style": 1,
      "name": "……음!\n들으면 들을수록 어려운 시험인 것 같지만\n반드시 합격하고 말겠어요![ST:wait ]"
    },
    {
      "$id": 29,
      "label": "tev026601_MSG0040",
      "style": 1,
      "name": "돌은 각각 보험에 들어 있어요\n숍 단말기로 살 때, 돌 보험이라는 항목에서\n그 횟수를 확인할 수 있어요[ST:wait ]"
    },
    {
      "$id": 30,
      "label": "tev026601_MSG0041",
      "style": 1,
      "name": "보험이 남아 있는 한\n망가져도 바로 돌려받을 수 있지만……[ST:wait ]"
    },
    {
      "$id": 31,
      "label": "tev026601_MSG0042",
      "style": 1,
      "name": "그렇다고 해서 돌을\n막 다뤄도 되는 건 아니에요![ST:wait ]"
    },
    {
      "$id": 32,
      "label": "tev026601_MSG0043",
      "style": 1,
      "name": "애써 손에 넣은 고액의 돌을\n메츠 씨처럼 원초의 황야에서 망가뜨리면\n호랑이 교관 울프 씨에게 혼날 거예요![ST:wait ]"
    },
    {
      "$id": 33,
      "label": "tev026601_MSG0048",
      "style": 1,
      "name": "그런 걸 만들다니……\n대단해, 너무 대단해요! 린은 신이에요![ST:wait ]"
    },
    {
      "$id": 34,
      "label": "tev026601_MSG0049",
      "style": 1,
      "name": "그게 있으면 아무리 험한 곳도\n돌로 날아갈 수 있고[ST:wait ]"
    },
    {
      "$id": 35,
      "label": "tev026601_MSG0050",
      "style": 1,
      "name": "지금까지 쓰러뜨릴 수 없었던 흉악한 적도\n상공에서 일방적으로 공격할 수 있는 데다가[ST:wait ]"
    },
    {
      "$id": 36,
      "label": "tev026601_MSG0051",
      "style": 1,
      "name": "높은 곳에서는 공격의 명중률도 높아지니까\n분명 이길 수 있을 거예요\n좋겠다~ 저도 빨리 만져 보고 싶어요![ST:wait ]"
    },
    {
      "$id": 37,
      "label": "tev026601_MSG0056",
      "style": 1,
      "name": "울프 씨를 보고 뒤에서 계속\n「호랑이 교관이다, 호랑이 교관이다」라고 했더니[ST:wait ]"
    },
    {
      "$id": 38,
      "label": "tev026601_MSG0057",
      "style": 1,
      "name": "결국 그렇게 부르는 걸 들켰어요……\n벼락이 떨어질 줄 알았는데\n신기하게도 혼나지 않았어요![ST:wait ]"
    },
    {
      "$id": 39,
      "label": "tev026601_MSG0058",
      "style": 1,
      "name": "……그 대신 왠지 슬픈 듯이\n「역시 호랑이구나」라고 중얼거리더니……[ST:wait ]"
    },
    {
      "$id": 40,
      "label": "tev026601_MSG0059",
      "style": 1,
      "name": "비틀비틀~하면서 어디론가 가 버렸어요[ST:wait ]"
    },
    {
      "$id": 41,
      "label": "tev026601_MSG0060",
      "style": 1,
      "name": "호랑이 교관의 이빨이 빠져서\n힘이 없어진 걸까요……?[ST:wait ]"
    }
  ]
}