{
  "schema": [
    {
      "name": "label",
      "type": 9
    },
    {
      "name": "style",
      "type": 2
    },
    {
      "name": "name",
      "type": 7
    }
  ],
  "rows": [
    {
      "$id": 1,
      "label": "tev072101_JNK0010",
      "style": 4,
      "name": "질문[ST:wait ]"
    },
    {
      "$id": 2,
      "label": "tev072101_SEL0011",
      "style": 3,
      "name": "그로우스에 있던 때에 관해 묻는다[ST:wait ]"
    },
    {
      "$id": 3,
      "label": "tev072101_JNK0020",
      "style": 4,
      "name": "흥미[ST:wait ]"
    },
    {
      "$id": 4,
      "label": "tev072101_SEL0021",
      "style": 3,
      "name": "곤란한 일이 있는지 묻는다[ST:wait ]"
    },
    {
      "$id": 5,
      "label": "tev072101_SEL0031",
      "style": 3,
      "name": "라스인에 관해 묻는다[ST:wait ]"
    },
    {
      "$id": 6,
      "label": "tev072101_SEL0051",
      "style": 3,
      "name": "그로우스에 붙잡혀 있던 자들에 관해 묻는다[ST:wait ]"
    },
    {
      "$id": 7,
      "label": "tev072101_SEL0071",
      "style": 3,
      "name": "그로우스에 붙잡혀 있던 자들에 관해 묻는다[ST:wait ]"
    },
    {
      "$id": 8,
      "label": "tev072101_SEL2021",
      "style": 3,
      "name": "곤란한 일이 있는지 묻는다[ST:wait ]"
    },
    {
      "$id": 9,
      "label": "tev072101_MSG0001",
      "style": 1,
      "name": "힘 있는 자가 우위에 서는 그로우스 안에서\n저희 오르페인은 바닥 취급을 받았습니다[ST:wait ]"
    },
    {
      "$id": 10,
      "label": "tev072101_MSG0002",
      "style": 1,
      "name": "끊임없이 신병기 개발을 강요받고\n조금이라도 쉬려고 하면 고문을 당하는[ST:wait ]"
    },
    {
      "$id": 11,
      "label": "tev072101_MSG0003",
      "style": 1,
      "name": "그런 가혹한 생활 가운데\n동료도 하나둘씩 죽어 가……[ST:wait ]"
    },
    {
      "$id": 12,
      "label": "tev072101_MSG0004",
      "style": 1,
      "name": "어떻게든 살아남은 것이\n당신께 구조된 5명의 오르페인이에요[ST:wait ]"
    },
    {
      "$id": 13,
      "label": "tev072101_MSG0005",
      "style": 1,
      "name": "그런 곳에는 이제 두 번 다시 돌아가고 싶지 않아요\n부디 그로우스로부터 저희를 지켜 주세요[ST:wait ]"
    },
    {
      "$id": 14,
      "label": "tev072101_MSG0010",
      "style": 1,
      "name": "눈을 감으면 오버에 의해 계승된\n고향의 모습이 되살아납니다……[ST:wait ]"
    },
    {
      "$id": 15,
      "label": "tev072101_MSG0011",
      "style": 1,
      "name": "짙은 녹색의 나무로 뒤덮인 마을에는\n몸을 감싸는 바람이 끝없이 불어와……\n거기 있는 것만으로도 생기가 차오르는 듯했죠[ST:wait ]"
    },
    {
      "$id": 16,
      "label": "tev072101_MSG0012",
      "style": 1,
      "name": "아아…… 그에 비해 여기는 어떤가요?\n나무는 조금밖에 없고\n무미건조한 콘크리트 집들뿐……[ST:wait ]"
    },
    {
      "$id": 17,
      "label": "tev072101_MSG0013",
      "style": 1,
      "name": "마치 감옥에 있는 기분이에요\n어서 식물학자 몬보이톤에게 부탁해서[ST:wait ]"
    },
    {
      "$id": 18,
      "label": "tev072101_MSG0014",
      "style": 1,
      "name": "NLA를 저희가 살기 좋은\n수목이 우거진 곳으로 바꿔야만 합니다……[ST:wait ]"
    },
    {
      "$id": 19,
      "label": "tev072101_MSG0019",
      "style": 1,
      "name": "그로우스에 붙잡혀 있던 때\n몇 번인가 라스인과 만난 적이 있는데요[ST:wait ]"
    },
    {
      "$id": 20,
      "label": "tev072101_MSG0020",
      "style": 1,
      "name": "그들은 저희를 학대하던 다른 그로우스의\n병사들과는 전혀 달랐습니다[ST:wait ]"
    },
    {
      "$id": 21,
      "label": "tev072101_MSG0021",
      "style": 1,
      "name": "그들의 돌…… 바사라를 수리하던 중\n과로로 쓰러져 버린 동료가 있었는데요[ST:wait ]"
    },
    {
      "$id": 22,
      "label": "tev072101_MSG0022",
      "style": 1,
      "name": "이를 책망하기는커녕\n쓰러진 동료를 돌보아 주며\n눈에 띄지 않는 곳에서 쉬게 해 주기도 했습니다[ST:wait ]"
    },
    {
      "$id": 23,
      "label": "tev072101_MSG0023",
      "style": 1,
      "name": "그 약자를 향한 상냥함……\n라스인에게는 지구인 여러분과\n조금 통하는 부분이 있는 것 같군요[ST:wait ]"
    },
    {
      "$id": 24,
      "label": "tev072101_MSG0028",
      "style": 1,
      "name": "저희 말고도 다양한 별에서 끌려와\n강제로 종속된 외계인이 있습니다[ST:wait ]"
    },
    {
      "$id": 25,
      "label": "tev072101_MSG0029",
      "style": 1,
      "name": "루크자르 사망 후 폭주한 부하들이\n그들에게 무엇을 할지 예상이 가지 않아요……[ST:wait ]"
    },
    {
      "$id": 26,
      "label": "tev072101_MSG0030",
      "style": 1,
      "name": "각지에 붙잡힌 외계인도\n구해 주지 않으시겠습니까?[ST:wait ]"
    },
    {
      "$id": 27,
      "label": "tev072101_MSG0031",
      "style": 1,
      "name": "분명 저희처럼 앞으로 이 미라에서\n살아가기 위한 큰 힘이 될 겁니다[ST:wait ]"
    },
    {
      "$id": 28,
      "label": "tev072101_MSG0036",
      "style": 1,
      "name": "그로우스가 멸망해 그들에게 붙잡혀 있던 외계인도\n대부분 NLA로 피난 왔습니다[ST:wait ]"
    },
    {
      "$id": 29,
      "label": "tev072101_MSG0037",
      "style": 1,
      "name": "오버가 없는 이들의 사고방식에는\n아직 친숙하지 않은 점도 많습니다만[ST:wait ]"
    },
    {
      "$id": 30,
      "label": "tev072101_MSG0038",
      "style": 1,
      "name": "저희도 이 도시의 일원으로서\n외계의 동료를 이해하고 싶습니다[ST:wait ]"
    },
    {
      "$id": 31,
      "label": "tev072101_MSG0039",
      "style": 1,
      "name": "앞으로도 다 같이\n그로우스와는 다른 형태의 외계 성간 연합……\n공생 관계를 쌓아 가지 않으시겠습니까?[ST:wait ]"
    },
    {
      "$id": 32,
      "label": "tev072101_MSG1001",
      "style": 1,
      "name": "그로우스에 붙잡혀 있던 때\n몇 번인가 라스인과 만난 적이 있는데요[ST:wait ]"
    },
    {
      "$id": 33,
      "label": "tev072101_MSG1002",
      "style": 1,
      "name": "그들은 저희를 학대하던 다른 그로우스의\n병사들과는 전혀 달랐습니다[ST:wait ]"
    },
    {
      "$id": 34,
      "label": "tev072101_MSG1003",
      "style": 1,
      "name": "그들의 돌…… 바사라를 수리하던 중\n과로로 쓰러져 버린 동료가 있었는데요[ST:wait ]"
    },
    {
      "$id": 35,
      "label": "tev072101_MSG1004",
      "style": 1,
      "name": "이를 책망하기는커녕\n쓰러진 동료를 돌보아 주며\n눈에 띄지 않는 곳에서 쉬게 해 주기도 했습니다[ST:wait ]"
    },
    {
      "$id": 36,
      "label": "tev072101_MSG1005",
      "style": 1,
      "name": "……흠, 이 바이어스인도\n조금은 그런 라스인의 상냥함을\n배워야 하는 게 아닐는지요?[ST:wait ]"
    },
    {
      "$id": 37,
      "label": "tev072101_MSG1010",
      "style": 1,
      "name": "……저는 언제까지\n이렇게 있어야 하는 걸까요?[ST:wait ]"
    },
    {
      "$id": 38,
      "label": "tev072101_MSG1011",
      "style": 1,
      "name": "단지 나무를 먹은 것만으로 이런 처사라니……\n바이어스인이란 참으로 무서운 종족입니다[ST:wait ]"
    },
    {
      "$id": 39,
      "label": "tev072101_MSG1012",
      "style": 1,
      "name": "마음껏 나무를 먹어도 괜찮도록\n식물학자인 몬보이톤이 하루빨리\nNLA를 바꿔 줬으면 하네요……[ST:wait ]"
    },
    {
      "$id": 40,
      "label": "tev072101_MSG1016",
      "style": 1,
      "name": "그로우스가 멸망해 그들에게 붙잡혀 있던 외계인도\n대부분 NLA로 피난 왔습니다[ST:wait ]"
    },
    {
      "$id": 41,
      "label": "tev072101_MSG1017",
      "style": 1,
      "name": "남은 건 서로 힘을 합쳐\n이 가혹한 미라에서 살아남는 것뿐……[ST:wait ]"
    },
    {
      "$id": 42,
      "label": "tev072101_MSG1018",
      "style": 1,
      "name": "……그런 걸 이 바이어스인도\n이해해 주셨으면 싶은 마음입니다만[ST:wait ]"
    },
    {
      "$id": 43,
      "label": "tev072101_MSG1019",
      "style": 1,
      "name": "흠, 이야기가 전혀 안 통합니다\n상호 이해란 어려운 것이로군요[ST:wait ]"
    }
  ]
}