{
  "schema": [
    {
      "name": "label",
      "type": 9
    },
    {
      "name": "style",
      "type": 2
    },
    {
      "name": "name",
      "type": 7
    }
  ],
  "rows": [
    {
      "$id": 1,
      "label": "tev910701_JNK0010",
      "style": 4,
      "name": "질문"
    },
    {
      "$id": 2,
      "label": "tev910701_SEL0020",
      "style": 3,
      "name": "스마일 피자에 관해"
    },
    {
      "$id": 3,
      "label": "tev910701_MSG0030",
      "style": 1,
      "name": "모두 싱글벙글~ 스마일 피자~\n피자의 정석~ 스마일 피자~[ST:wait ]"
    },
    {
      "$id": 4,
      "label": "tev910701_MSG0040",
      "style": 1,
      "name": "토핑 추가도 접수 중~\n현재 오픈 기념으로 특별 쿠폰 배포 중~[ST:wait ]"
    },
    {
      "$id": 5,
      "label": "tev910701_MSG0050",
      "style": 1,
      "name": "하아…… 내가 지금 뭘 하는 건지[ST:wait ]"
    },
    {
      "$id": 6,
      "label": "tev910701_JNK0060",
      "style": 4,
      "name": "흥미"
    },
    {
      "$id": 7,
      "label": "tev910701_SEL0070",
      "style": 3,
      "name": "최근 상황을 묻는다"
    },
    {
      "$id": 8,
      "label": "tev910701_MSG0080",
      "style": 1,
      "name": "아버지가 암즈 컴퍼니 중역인데\n옛날부터 호랑이처럼 엄해서 말이죠……[ST:wait ]"
    },
    {
      "$id": 9,
      "label": "tev910701_MSG0090",
      "style": 1,
      "name": "인류를 위해 사회에 공헌하라면서\n절 주택 에어리어에서 쫓아냈어요[ST:wait ]"
    },
    {
      "$id": 10,
      "label": "tev910701_MSG0100",
      "style": 1,
      "name": "일단 먹고살 돈을 벌기 위해\n스마일 피자에서 일하게 됐지만……[ST:wait ]"
    },
    {
      "$id": 11,
      "label": "tev910701_MSG0110",
      "style": 1,
      "name": "아~아, 저도 블레이드처럼\n멋있게 싸울 수 있다면……[ST:wait ]"
    },
    {
      "$id": 12,
      "label": "tev910701_JNK0120",
      "style": 4,
      "name": "질문"
    },
    {
      "$id": 13,
      "label": "tev910701_SEL0130",
      "style": 3,
      "name": "스마일 피자의 판매량에 관해"
    },
    {
      "$id": 14,
      "label": "tev910701_MSG0140",
      "style": 1,
      "name": "그럭저럭 괜찮아요\n마 논인 손님이 늘어나서\n전보다 피자가 잘 팔리게 됐으니까[ST:wait ]"
    },
    {
      "$id": 15,
      "label": "tev910701_MSG0150",
      "style": 1,
      "name": "뭐, 아미 피자 가게에 비교하면\n손님 수는 한참 부족하지만요[ST:wait ]"
    },
    {
      "$id": 16,
      "label": "tev910701_MSG0160",
      "style": 1,
      "name": "저쪽은 엄청 바빠 보이는데\n역시 잘되는 곳은 다르네요[ST:wait ]"
    },
    {
      "$id": 17,
      "label": "tev910701_JNK0170",
      "style": 4,
      "name": "흥미"
    },
    {
      "$id": 18,
      "label": "tev910701_SEL0180",
      "style": 3,
      "name": "최근 상황을 묻는다"
    },
    {
      "$id": 19,
      "label": "tev910701_MSG0190",
      "style": 1,
      "name": "마 논인 손님은\n한 번에 대량으로 주문하는 사람이 많아서\n좀 곤란하단 말이죠……[ST:wait ]"
    },
    {
      "$id": 20,
      "label": "tev910701_MSG0200",
      "style": 1,
      "name": "재료가 금방 떨어져 버리고\n그렇다고 사들이는 데에도 한계가 있고[ST:wait ]"
    },
    {
      "$id": 21,
      "label": "tev910701_MSG0210",
      "style": 1,
      "name": "하아…… 또 컴패니언에게\n식재료를 조달해 달라고 의뢰해야겠네[ST:wait ]"
    },
    {
      "$id": 22,
      "label": "tev910701_JNK0220",
      "style": 4,
      "name": "질문"
    },
    {
      "$id": 23,
      "label": "tev910701_SEL0230",
      "style": 3,
      "name": "알에 관해"
    },
    {
      "$id": 24,
      "label": "tev910701_MSG0240",
      "style": 1,
      "name": "처음 봤을 때는 분위기가 너무 달라서\n몰라봤지만……[ST:wait ]"
    },
    {
      "$id": 25,
      "label": "tev910701_MSG0250",
      "style": 1,
      "name": "그 조금 무서운 형이\n흰고래를 구한 영웅……\n알로이스 브루놀트라는 게 사실인가요……?[ST:wait ]"
    },
    {
      "$id": 26,
      "label": "tev910701_MSG0260",
      "style": 1,
      "name": "아~아…… 그런 줄 알았으면\n사인을 받았을 텐데……[ST:wait ]"
    },
    {
      "$id": 27,
      "label": "tev910701_JNK0270",
      "style": 4,
      "name": "흥미"
    },
    {
      "$id": 28,
      "label": "tev910701_SEL0280",
      "style": 3,
      "name": "최근 상황을 묻는다"
    },
    {
      "$id": 29,
      "label": "tev910701_MSG0290",
      "style": 1,
      "name": "그 멋있는 형 덕분에\n뭐랄까, 저…… 정신이 들었어요[ST:wait ]"
    },
    {
      "$id": 30,
      "label": "tev910701_MSG0300",
      "style": 1,
      "name": "아버지 일로 불평할 시간이 있으면\n피자를 한 판이라도 더 구워서\n손님에게 전해 주는 게 낫다고……[ST:wait ]"
    },
    {
      "$id": 31,
      "label": "tev910701_MSG0310",
      "style": 1,
      "name": "요즘은 일에도 점점 보람이 느껴지고\n드디어 점장님도 급료를 올려 줬고……[ST:wait ]"
    },
    {
      "$id": 32,
      "label": "tev910701_MSG0320",
      "style": 1,
      "name": "뭐, 아무튼……\n후회투성이 인생이 되지 않도록\n지금은 열심히 해 볼게요[ST:wait ]"
    },
    {
      "$id": 33,
      "label": "tev910701_MSG0330",
      "style": 4,
      "name": "취소"
    },
    {
      "$id": 34,
      "label": "tev910701_MSG0340",
      "style": 3,
      "name": "취소"
    }
  ]
}