{
  "schema": [
    {
      "name": "label",
      "type": 9
    },
    {
      "name": "style",
      "type": 2
    },
    {
      "name": "name",
      "type": 7
    }
  ],
  "rows": [
    {
      "$id": 1,
      "label": "qev025603_MSG0001",
      "style": 1,
      "name": "なっ……なんだい！？\nこのマ・ノンに　店の外に\n連れてこられたんだけど……[ST:wait ]"
    },
    {
      "$id": 2,
      "label": "qev025603_MSG0002",
      "style": 1,
      "name": "あたしゃ今　仕事中なんだよ\n用があるなら早くしておくれよ[ST:wait ]"
    },
    {
      "$id": 3,
      "label": "qev025603_MSG0003",
      "style": 1,
      "name": "ぐすっ……ボビーは\n忘却の渓谷のデビルズコロニーで\n命を落としたんだ……[ST:wait ]"
    },
    {
      "$id": 4,
      "label": "qev025603_MSG0004",
      "style": 1,
      "name": "もし腕時計があるとすれば\nきっと　そこら辺にあるはずだよ[ST:wait ]"
    },
    {
      "$id": 5,
      "label": "qev025603_MSG0005",
      "style": 1,
      "name": "でも……どうしてそこまでしてくれるんだい？\nあんた達は一体　何者なんだい？[ST:wait ]"
    },
    {
      "$id": 6,
      "label": "qev025603_MSG0006",
      "style": 1,
      "name": "ううっ……必死にこらえて仕事してたんだけど\nあんた達が変なこというから\nすっかり思い出しちまったよ……[ST:wait ]"
    },
    {
      "$id": 7,
      "label": "qev025603_MSG0007",
      "style": 1,
      "name": "いつだったか　あの子……\n皿洗いしてるあたしに　水仕事は大変だろって\nハンドクリームをくれたんだ[ST:wait ]"
    },
    {
      "$id": 8,
      "label": "qev025603_MSG0008",
      "style": 1,
      "name": "うちのお店には沢山のブレイドが来るけど\nそんな風に気遣ってくれたのは\nボビーくらいだったよ……ぐすっ……[ST:wait ]"
    },
    {
      "$id": 9,
      "label": "qev025603_MSG0009",
      "style": 1,
      "name": "『悲しみ』のデータは十分取れました\nさぁ　早く腕時計を渡して\n脳波を正常値に戻してください[ST:wait ]"
    },
    {
      "$id": 10,
      "label": "qev025603_MSG0010",
      "style": 1,
      "name": "これは……！\n確かにボビーの腕時計……[ST:wait ]"
    },
    {
      "$id": 11,
      "label": "qev025603_MSG0011",
      "style": 1,
      "name": "ああっ　ありがとう……\nこいつは　ボビーが初めて戦場に出る時に\nあたしが記念に贈ってやったものなんだ[ST:wait ]"
    },
    {
      "$id": 12,
      "label": "qev025603_MSG0012",
      "style": 1,
      "name": "……なんだかこうして握りしめていると\nあの子が近くにいてくれている気がするよ[ST:wait ]"
    },
    {
      "$id": 13,
      "label": "qev025603_MSG0013",
      "style": 1,
      "name": "おおっ！　値がみるみる下がって行きます！\nふぅむ……腕時計とは時間を報せるだけでなく\n『悲しみ』を低下させる機能もあるんですね[ST:wait ]"
    },
    {
      "$id": 14,
      "label": "qev025603_JNK0010",
      "style": 4,
      "name": "否定"
    },
    {
      "$id": 15,
      "label": "qev025603_SEL0011",
      "style": 3,
      "name": "チオピッタスにポーレンの\n心の変化について説明する"
    },
    {
      "$id": 16,
      "label": "qev025603_JNK0020",
      "style": 4,
      "name": "放っておく"
    },
    {
      "$id": 17,
      "label": "qev025603_SEL0021",
      "style": 3,
      "name": "チオピッタスの誤解を\nそのままにしておく"
    },
    {
      "$id": 18,
      "label": "qev025603_MSG0014",
      "style": 1,
      "name": "イタワリの気持ち？　死者をシノブ？\n何の専門用語ですか　それは？[ST:wait ]"
    },
    {
      "$id": 19,
      "label": "qev025603_MSG0015",
      "style": 1,
      "name": "まぁいいです　データは取れましたから\nこれを解析すれば私は\n地球人の『悲しみ』を理解できるはずです[ST:wait ]"
    },
    {
      "$id": 20,
      "label": "qev025603_MSG0016",
      "style": 1,
      "name": "今度　『悲しみ』の状態にある\n地球人に遭遇したら\n私も腕時計を与えてみることにします[ST:wait ]"
    },
    {
      "$id": 21,
      "label": "qev025603_MSG0017",
      "style": 1,
      "name": "ふふっ　もっともっと沢山の\n『悲しみ』のデータが欲しいものです[ST:wait ]"
    },
    {
      "$id": 22,
      "label": "qev025603_MSG0018",
      "style": 1,
      "name": "……あっ……ああっ！！[ST:wait ]"
    },
    {
      "$id": 23,
      "label": "qev025603_MSG0019",
      "style": 1,
      "name": "どうしましたか！？\n平常値に戻った感情が\n急に跳ね上がりましたよ！[ST:wait ]"
    },
    {
      "$id": 24,
      "label": "qev025603_MSG0020",
      "style": 1,
      "name": "……腕時計の裏に……\n『マザーポーレンの加護あれ！』って\nあの子の字が…………！[ST:wait ]"
    },
    {
      "$id": 25,
      "label": "qev025603_MSG0021",
      "style": 1,
      "name": "なんだってんだい……ううっ……！\nあたしのことを母親だなんて……\nあの子ったら　本当にバカな子だね[ST:wait ]"
    },
    {
      "$id": 26,
      "label": "qev025603_MSG0022",
      "style": 1,
      "name": "うーん……先程の『悲しみ』とは\n脳波が違う揺れ方をしていますね……\n『悲しみ』とは複雑なものです[ST:wait ]"
    },
    {
      "$id": 27,
      "label": "qev025603_MSG0023",
      "style": 1,
      "name": "……まぁいいです\n次のサンプルの下へ行きましょう\n先程の場所に戻ってきてください[ST:wait ]"
    },
    {
      "$id": 28,
      "label": "qev025603_MSG0024",
      "style": 1,
      "name": "この腕時計……大切に取っておくよ\nセントラルライフから\nいつかあの子が帰ってきたら　返してやるんだ[ST:wait ]"
    },
    {
      "$id": 29,
      "label": "qev025603_MSG0025",
      "style": 1,
      "name": "……ありがとうね\nあの妙なマ・ノンにも\nお礼を言っておいてちょうだいよ[ST:wait ]"
    },
    {
      "$id": 30,
      "label": "qev025603_MSG0026",
      "style": 1,
      "name": "あのさ……次々とライフって\n壊されちゃってるんだろ？\nセントラルライフは……大丈夫だよね[ST:wait ]"
    },
    {
      "$id": 31,
      "label": "qev025603_MSG0027",
      "style": 1,
      "name": "そいつがなくなっちまったら\nレストランで楽しそうに談笑してるお客さんが\nいきなりみんな　パタッと死んじまうんだ[ST:wait ]"
    },
    {
      "$id": 32,
      "label": "qev025603_MSG0028",
      "style": 1,
      "name": "そんなことにならないように……\n早く見つけておくれよ　頼んだよ？[ST:wait ]"
    }
  ]
}