{
  "schema": [
    {
      "name": "label",
      "type": 9
    },
    {
      "name": "style",
      "type": 2
    },
    {
      "name": "name",
      "type": 7
    }
  ],
  "rows": [
    {
      "$id": 1,
      "label": "tev014901_JNK0010",
      "style": 4,
      "name": "質問"
    },
    {
      "$id": 2,
      "label": "tev014901_SEL0011",
      "style": 3,
      "name": "イリーナチームの\n戦い方について聞く"
    },
    {
      "$id": 3,
      "label": "tev014901_JNK0020",
      "style": 4,
      "name": "興味"
    },
    {
      "$id": 4,
      "label": "tev014901_SEL0021",
      "style": 3,
      "name": "困っていることを尋ねる"
    },
    {
      "$id": 5,
      "label": "tev014901_SEL0031",
      "style": 3,
      "name": "忘却の渓谷での\n戦闘について聞く"
    },
    {
      "$id": 6,
      "label": "tev014901_SEL1021",
      "style": 3,
      "name": "最近の様子を尋ねる"
    },
    {
      "$id": 7,
      "label": "tev014901_MSG0001",
      "style": 1,
      "name": "うちのチームじゃ　でっかい討伐任務の前は\nチームリーダーのイリーナさんを囲んで[ST:wait ]"
    },
    {
      "$id": 8,
      "label": "tev014901_MSG0002",
      "style": 1,
      "name": "エネミー図鑑の情報を見て　作戦を立ててから\n戦いに行くってのが約束事になってるんです[ST:wait ]"
    },
    {
      "$id": 9,
      "label": "tev014901_MSG0003",
      "style": 1,
      "name": "支給された端末を使えば　いつでも\n今まで戦った敵の情報が見られますから[ST:wait ]"
    },
    {
      "$id": 10,
      "label": "tev014901_MSG0004",
      "style": 1,
      "name": "あなたもぜひ　有効活用して\nミラでの厳しい戦いを　生き延びてくださいね[ST:wait ]"
    },
    {
      "$id": 11,
      "label": "tev014901_MSG0008",
      "style": 1,
      "name": "イリーナさん　つまんないブレイド野郎に\nよく絡まれるんですよ[ST:wait ]"
    },
    {
      "$id": 12,
      "label": "tev014901_MSG0009",
      "style": 1,
      "name": "ああいうのって\nイリーナさんのことが気になるから\nちょっかい出してるんでしょうが[ST:wait ]"
    },
    {
      "$id": 13,
      "label": "tev014901_MSG0010",
      "style": 1,
      "name": "いい歳してつまらない事しますよね……\n素直に飲みに誘うとかすればいいのに[ST:wait ]"
    },
    {
      "$id": 14,
      "label": "tev014901_MSG0015",
      "style": 1,
      "name": "[ST:playername ]さん\n忘却の渓谷では……ありがとうございました[ST:wait ]"
    },
    {
      "$id": 15,
      "label": "tev014901_MSG0016",
      "style": 1,
      "name": "あの時　エルマ大佐が声をかけてくれなければ\n今頃　自分とイリーナさんは[ST:wide ]―[ST:wait ]"
    },
    {
      "$id": 16,
      "label": "tev014901_MSG0020",
      "style": 1,
      "name": "何暗くなってんだよ！\nもし　エルマ大佐が声をかけてくれなくても\nあたしがマーカスを突き飛ばしてやってたさ[ST:wait ]"
    },
    {
      "$id": 17,
      "label": "tev014901_MSG0021",
      "style": 1,
      "name": "ええっ！？　それって攻撃が当たるより\n大怪我しそうじゃないですか？[ST:wait ]"
    },
    {
      "$id": 18,
      "label": "tev014901_MSG0022",
      "style": 1,
      "name": "マーカス　お前　受け身くらい取れるだろ？\nなんたって　あたしが認めた\n優秀なメンバーの一員なんだからな！[ST:wait ]"
    },
    {
      "$id": 19,
      "label": "tev014901_MSG0023",
      "style": 1,
      "name": "それはまあ　そうですけど……\n全く　イリーナさんには敵わないなぁ[ST:wait ]"
    },
    {
      "$id": 20,
      "label": "tev014901_MSG0025",
      "style": 1,
      "name": "すみません　湿っぽくなって\nははっ　ケガしてもB.B.だから大丈夫だとは\n分かっているんですがね……[ST:wait ]"
    },
    {
      "$id": 21,
      "label": "tev014901_MSG0026",
      "style": 1,
      "name": "エルマ大佐のように　敵の思惑を読んで\n確実に生き延びる行動を　心掛けますよ！[ST:wait ]"
    },
    {
      "$id": 22,
      "label": "tev014901_MSG1018",
      "style": 1,
      "name": "イリーナさんにちょっかい出してたブレイド\n少しは反省したみたいですね[ST:wait ]"
    },
    {
      "$id": 23,
      "label": "tev014901_MSG1019",
      "style": 1,
      "name": "こないだ　イリーナ姐さんにって\nいい酒とつまみを　届けに来ましたよ[ST:wait ]"
    },
    {
      "$id": 24,
      "label": "tev014901_MSG1020",
      "style": 1,
      "name": "男に関しては　色々あったみたいですが\nこれを機会に少し落ち着くといいですね[ST:wait ]"
    }
  ]
}