{
  "schema": [
    {
      "name": "label",
      "type": 9
    },
    {
      "name": "style",
      "type": 2
    },
    {
      "name": "name",
      "type": 7
    }
  ],
  "rows": [
    {
      "$id": 1,
      "label": "tev045901_JNK0010",
      "style": 4,
      "name": "質問[ST:wait ]"
    },
    {
      "$id": 2,
      "label": "tev045901_SEL0011",
      "style": 3,
      "name": "バイアス人の\n性格について聞く[ST:wait ]"
    },
    {
      "$id": 3,
      "label": "tev045901_JNK0020",
      "style": 4,
      "name": "興味[ST:wait ]"
    },
    {
      "$id": 4,
      "label": "tev045901_SEL0021",
      "style": 3,
      "name": "困っていることを尋ねる[ST:wait ]"
    },
    {
      "$id": 5,
      "label": "tev045901_SEL1021",
      "style": 3,
      "name": "最近の様子を尋ねる"
    },
    {
      "$id": 6,
      "label": "tev045901_SEL1031",
      "style": 3,
      "name": "グロウスについて聞く"
    },
    {
      "$id": 7,
      "label": "tev045901_SEL1051",
      "style": 3,
      "name": "ラオの裏切りについて聞く"
    },
    {
      "$id": 8,
      "label": "tev045901_SEL1071",
      "style": 3,
      "name": "これからのことについて聞く"
    },
    {
      "$id": 9,
      "label": "tev045901_MSG0001",
      "style": 1,
      "name": "あんたらは　ずーっと巌窟の一族と\n戦ってきたみたいだしね[ST:wait ]"
    },
    {
      "$id": 10,
      "label": "tev045901_MSG0002",
      "style": 1,
      "name": "あたしらのこと　卑劣で\n乱暴な大食らいだって思ってるナ？[ST:wait ]"
    },
    {
      "$id": 11,
      "label": "tev045901_MSG0003",
      "style": 1,
      "name": "大食らい……は変わらないけどさ\n戦さえなきゃ　あたしら大樹の一族は\n穏やかで陽気な種族なんだ[ST:wait ]"
    },
    {
      "$id": 12,
      "label": "tev045901_MSG0004",
      "style": 1,
      "name": "踊りと楽しいお酒が好きでね\n大きい獲物が捕れた時なんか　祭りを開いて\nいつも朝まで騒ぎ続けてたもんさ[ST:wait ]"
    },
    {
      "$id": 13,
      "label": "tev045901_MSG0005",
      "style": 1,
      "name": "あたしはさ　確かにグロウスも憎いけど……\nこのしみったれた戦が終わって欲しいんだナ\n昔みたいな　みんなの笑顔が見たいよ[ST:wait ]"
    },
    {
      "$id": 14,
      "label": "tev045901_MSG0008",
      "style": 1,
      "name": "テアがフィアンセを亡くしてから\nずっと落ち込みっぱなしでナ[ST:wait ]"
    },
    {
      "$id": 15,
      "label": "tev045901_MSG0009",
      "style": 1,
      "name": "なんとかしてあげたいんだけど……\nちょっと　あたしだけじゃ\nどうしようもなさそうなんダ[ST:wait ]"
    },
    {
      "$id": 16,
      "label": "tev045901_MSG0010",
      "style": 1,
      "name": "……なぁ　ブレイドってのは異星人の……\n個人的な頼み事なんかも聞いてくれるのかナ？[ST:wait ]"
    },
    {
      "$id": 17,
      "label": "tev045901_MSG0011",
      "style": 1,
      "name": "もし聞いてもらえそうってんなら\n落ち着いたら　ブレイドを探してみようかナ？[ST:wait ]"
    },
    {
      "$id": 18,
      "label": "tev045901_MSG0012",
      "style": 1,
      "name": "早く元気になってもらって……\n昔みたいに　踊ってもらいたいんだよ[ST:wait ]"
    },
    {
      "$id": 19,
      "label": "tev045901_MSG0013",
      "style": 1,
      "name": "……実はね　あたしも昔はダンサーだったんだ\nテアの母親と一緒に　大樹の一族で\n一番の踊り手を目指して頑張ってたもんさ[ST:wait ]"
    },
    {
      "$id": 20,
      "label": "tev045901_MSG0014",
      "style": 1,
      "name": "だけど　巌窟の一族との戦争で\n足をやられちまって……夢を諦めなきゃ\nいけなくなっちゃったんだナ[ST:wait ]"
    },
    {
      "$id": 21,
      "label": "tev045901_MSG0015",
      "style": 1,
      "name": "だから　テアが踊っている姿を見ていると\nなんだか自分もあの頃みたいに\n踊れているような気持ちになってナ……[ST:wait ]"
    },
    {
      "$id": 22,
      "label": "tev045901_MSG0016",
      "style": 1,
      "name": "とっても幸せな気持ちになれるんだナ\n本当にありがとうナ！[ST:wait ]"
    },
    {
      "$id": 23,
      "label": "tev045901_MSG0017",
      "style": 1,
      "name": "テアなら　工業エリアのダイナーへ\n踊りに行ったから　一度見てみてよ！[ST:wait ]"
    },
    {
      "$id": 24,
      "label": "tev045901_MSG0018",
      "style": 1,
      "name": "きっとあんたも\nあの子の踊りのトリコになるはずナ！[ST:wait ]"
    },
    {
      "$id": 25,
      "label": "tev045901_MSG1001",
      "style": 1,
      "name": "あたしらバイアス人だって　一万年もの間\n戦争を続けてきた好戦的な種族だけど\nグロウスの連中と比べたらかわいいもんさ[ST:wait ]"
    },
    {
      "$id": 26,
      "label": "tev045901_MSG1002",
      "style": 1,
      "name": "アイツらにとって戦争をし　略奪することは\n息を吸ってゴハンを食べるようなものなんだ[ST:wait ]"
    },
    {
      "$id": 27,
      "label": "tev045901_MSG1003",
      "style": 1,
      "name": "地球人は良くやってるけどさ……\nグロウスの攻撃は\nきっとこんなものじゃ収まらない[ST:wait ]"
    },
    {
      "$id": 28,
      "label": "tev045901_MSG1004",
      "style": 1,
      "name": "もっともっと卑怯な手を使ってくるはずだから\n注意しておくんだナ[ST:wait ]"
    },
    {
      "$id": 29,
      "label": "tev045901_MSG1009",
      "style": 1,
      "name": "グロウスがブレイドをたぶらかして\n貴重なデータを盗み出そうとしたんだろ？[ST:wait ]"
    },
    {
      "$id": 30,
      "label": "tev045901_MSG1010",
      "style": 1,
      "name": "アイツら　あたし達の時だって\n巌窟の一族をそそのかして\n自分の手を汚さずに　捕らえさせたんだ……[ST:wait ]"
    },
    {
      "$id": 31,
      "label": "tev045901_MSG1011",
      "style": 1,
      "name": "本当に薄汚い連中さ……\nあんたも　あんな奴らに絶対負けちゃダメだよ[ST:wait ]"
    },
    {
      "$id": 32,
      "label": "tev045901_MSG1016",
      "style": 1,
      "name": "グロウスの親玉がいなくなって\n巌窟の一族も　散り散りになっていった……[ST:wait ]"
    },
    {
      "$id": 33,
      "label": "tev045901_MSG1017",
      "style": 1,
      "name": "ずーっと戦争を続けてきた　あたしらに\n一万年ぶりの平和が訪れたのかもしれないナ[ST:wait ]"
    },
    {
      "$id": 34,
      "label": "tev045901_MSG1018",
      "style": 1,
      "name": "なんだか……嬉しいねぇ\nこれからは誰も死なず　誰も殺さず[ST:wait ]"
    },
    {
      "$id": 35,
      "label": "tev045901_MSG1019",
      "style": 1,
      "name": "ただ日々をしっかりと生きて\n嬉しいことがあれば\n皆で輪になって踊ってそれを分かち合う[ST:wait ]"
    },
    {
      "$id": 36,
      "label": "tev045901_MSG1020",
      "style": 1,
      "name": "そんな　信じられないくらい甘くて\n平和な生活を積み重ねていけるんだナ……[ST:wait ]"
    }
  ]
}