{
  "schema": [
    {
      "name": "label",
      "type": 9
    },
    {
      "name": "style",
      "type": 2
    },
    {
      "name": "name",
      "type": 7
    }
  ],
  "rows": [
    {
      "$id": 1,
      "label": "tev022701_JNK0010",
      "style": 4,
      "name": "質問"
    },
    {
      "$id": 2,
      "label": "tev022701_SEL0011",
      "style": 3,
      "name": "NLAの施設について聞く"
    },
    {
      "$id": 3,
      "label": "tev022701_JNK0020",
      "style": 4,
      "name": "興味"
    },
    {
      "$id": 4,
      "label": "tev022701_SEL0021",
      "style": 3,
      "name": "噂話を聞く"
    },
    {
      "$id": 5,
      "label": "tev022701_SEL0031",
      "style": 3,
      "name": "いますぐドールに\n搭乗できないかと聞く"
    },
    {
      "$id": 6,
      "label": "tev022701_SEL0051",
      "style": 3,
      "name": "グロウスの兵器について聞く"
    },
    {
      "$id": 7,
      "label": "tev022701_SEL0071",
      "style": 3,
      "name": "ドールの特性について聞く"
    },
    {
      "$id": 8,
      "label": "tev022701_SEL0091",
      "style": 3,
      "name": "グロウスの兵器について聞く"
    },
    {
      "$id": 9,
      "label": "tev022701_SEL1021",
      "style": 3,
      "name": "噂話を聞く"
    },
    {
      "$id": 10,
      "label": "tev022701_SEL0111",
      "style": 3,
      "name": "プログアレスについて聞く"
    },
    {
      "$id": 11,
      "label": "tev022701_SEL3021",
      "style": 3,
      "name": "最近の様子を尋ねる"
    },
    {
      "$id": 12,
      "label": "tev022701_MSG0001",
      "style": 1,
      "name": "ブレイドエリアの\nショップ街には行きましたか？[ST:wait ]"
    },
    {
      "$id": 13,
      "label": "tev022701_MSG0002",
      "style": 1,
      "name": "あそこでは　様々な企業の\nインナー装備が買える上にですね[ST:wait ]"
    },
    {
      "$id": 14,
      "label": "tev022701_MSG0003",
      "style": 1,
      "name": "サクラバ製のドールなども\n購入することができるんですよ？[ST:wait ]"
    },
    {
      "$id": 15,
      "label": "tev022701_MSG0004",
      "style": 1,
      "name": "どれとは機密上言えませんが\n私が設計を手掛けた兵装などもありまして……[ST:wait ]"
    },
    {
      "$id": 16,
      "label": "tev022701_MSG0005",
      "style": 1,
      "name": "それらが　あなた方のお役に立てること\n心より願っています[ST:wait ]"
    },
    {
      "$id": 17,
      "label": "tev022701_MSG0006",
      "style": 1,
      "name": "ウエストゲートを出て　道なりに北西に進めば\nブレイド達が駐在する\nビアーノ草原ベースキャンプがあるのですが[ST:wait ]"
    },
    {
      "$id": 18,
      "label": "tev022701_MSG0007",
      "style": 1,
      "name": "そのもっと先の『緑の洞門』を抜けた場所に\n夜光の森という大森林があるらしいですね[ST:wait ]"
    },
    {
      "$id": 19,
      "label": "tev022701_MSG0008",
      "style": 1,
      "name": "とても複雑な地形をしているらしく\n何人ものブレイドが\nその森で　行方不明になっていると聞きました[ST:wait ]"
    },
    {
      "$id": 20,
      "label": "tev022701_MSG0009",
      "style": 1,
      "name": "あなたも任務で夜光の森に\n向かうことがあれば\n十分に注意して行ってくださいね[ST:wait ]"
    },
    {
      "$id": 21,
      "label": "tev022701_MSG0014",
      "style": 1,
      "name": "NLAの生産システムでは\nまだ満足にドールの量産化が行えず[ST:wait ]"
    },
    {
      "$id": 22,
      "label": "tev022701_MSG0015",
      "style": 1,
      "name": "なかなか　あなたのような新人ブレイドにまで\n配備が行き届かないのが現状なんです[ST:wait ]"
    },
    {
      "$id": 23,
      "label": "tev022701_MSG0016",
      "style": 1,
      "name": "今は　ドールライセンス制度を設けて\nドールに搭乗できる者を　ライセンス所持者に\n限定させていただいているんですよ……[ST:wait ]"
    },
    {
      "$id": 24,
      "label": "tev022701_MSG0017",
      "style": 1,
      "name": "不眠不休で研究に当たり　必ずやこのミラでも\nドールの量産体制を整えてみせますから……\nすいませんが　もうしばらくお待ちください[ST:wait ]"
    },
    {
      "$id": 25,
      "label": "tev022701_MSG0021",
      "style": 1,
      "name": "夜光の森で遭遇した\nゲーティアという異星人ですが[ST:wait ]"
    },
    {
      "$id": 26,
      "label": "tev022701_MSG0022",
      "style": 1,
      "name": "妙なエネルギー攻撃を使い\nブレイドを苦しめたらしいですね[ST:wait ]"
    },
    {
      "$id": 27,
      "label": "tev022701_MSG0023",
      "style": 1,
      "name": "我々が　今まで作ってきた装備では\nそのような攻撃を防ぎきることは\nできませんし……[ST:wait ]"
    },
    {
      "$id": 28,
      "label": "tev022701_MSG0024",
      "style": 1,
      "name": "早く　エネルギービームコーティングに\n特化した新装備を開発しなければなりません[ST:wait ]"
    },
    {
      "$id": 29,
      "label": "tev022701_MSG0025",
      "style": 1,
      "name": "我々研究者も出来る限りのことはしますから\nあなたも　多くの『設計図』を集めて\n兵器開発にご協力ください[ST:wait ]"
    },
    {
      "$id": 30,
      "label": "tev022701_MSG0030",
      "style": 1,
      "name": "もちろん　その機動力の高さこそが\nドール最大の武器ですが[ST:wait ]"
    },
    {
      "$id": 31,
      "label": "tev022701_MSG0031",
      "style": 1,
      "name": "ドールを稼働させるジェネレーターの\n高いエネルギー出力を活かした[ST:wait ]"
    },
    {
      "$id": 32,
      "label": "tev022701_MSG0032",
      "style": 1,
      "name": "数々の高火力兵器の破壊力もまた\nドールならではの強みだと言えます[ST:wait ]"
    },
    {
      "$id": 33,
      "label": "tev022701_MSG0033",
      "style": 1,
      "name": "通常兵器では　傷つけることすらできない\nオーバードもいると思いますが[ST:wait ]"
    },
    {
      "$id": 34,
      "label": "tev022701_MSG0034",
      "style": 1,
      "name": "ドールに搭乗すれば　そのような敵の装甲をも\n打ち砕けるようになるはずですよ[ST:wait ]"
    },
    {
      "$id": 35,
      "label": "tev022701_MSG0039",
      "style": 1,
      "name": "我々研究者は　なかなか動いている\nグロウスの機体を見る機会がありませんからね[ST:wait ]"
    },
    {
      "$id": 36,
      "label": "tev022701_MSG0040",
      "style": 1,
      "name": "襲撃中　徘徊するグロウスの機体群を\nモニターで見て　興奮してしまいましたよ[ST:wait ]"
    },
    {
      "$id": 37,
      "label": "tev022701_MSG0041",
      "style": 1,
      "name": "あの破壊力　機動力[ST:wide ]―\nさすがは地球を　ああも簡単に滅ぼした者達の\nテクノロジーといったところですか[ST:wait ]"
    },
    {
      "$id": 38,
      "label": "tev022701_MSG0042",
      "style": 1,
      "name": "メレデス＆コーの技術者が　躍起になって\n彼らの兵器を研究しているのも理解できますね[ST:wait ]"
    },
    {
      "$id": 39,
      "label": "tev022701_MSG0047",
      "style": 1,
      "name": "ラオさんが奪ったあの機体[ST:wide ]―\nまだ開発段階だったというのに\n凄まじい力を有していたようですね[ST:wait ]"
    },
    {
      "$id": 40,
      "label": "tev022701_MSG0048",
      "style": 1,
      "name": "今後の研究のために\n我々　アームズカンパニー側の技術者にも[ST:wait ]"
    },
    {
      "$id": 41,
      "label": "tev022701_MSG0049",
      "style": 1,
      "name": "元となった『アレス』の情報を\n開示して欲しいと本部にかけあったのですが[ST:wait ]"
    },
    {
      "$id": 42,
      "label": "tev022701_MSG0050",
      "style": 1,
      "name": "ふぅ……断られてしまいましたよ[ST:wait ]"
    },
    {
      "$id": 43,
      "label": "tev022701_MSG0051",
      "style": 1,
      "name": "どうやら　あれの元となった機体は\n本部が所有する他の兵器とは\nまるで別種の『何か』みたいですね[ST:wait ]"
    },
    {
      "$id": 44,
      "label": "tev022701_MSG1001",
      "style": 1,
      "name": "アームズ性能試験場の壁沿いの道に\nロブスターのぬいぐるみが\n捨てられていたんですが……[ST:wait ]"
    },
    {
      "$id": 45,
      "label": "tev022701_MSG1002",
      "style": 1,
      "name": "あれ　なんですかね……\n誰があんな所に捨てていったんでしょうか……[ST:wait ]"
    },
    {
      "$id": 46,
      "label": "tev022701_MSG2001",
      "style": 1,
      "name": "リヴィアは　私のつまらない話を\n真剣に聞いてくれた……とても良い人だった[ST:wait ]"
    },
    {
      "$id": 47,
      "label": "tev022701_MSG2002",
      "style": 1,
      "name": "女性の彼女を　愛することはできませんが……[ST:wait ]"
    },
    {
      "$id": 48,
      "label": "tev022701_MSG2003",
      "style": 1,
      "name": "いつか友人として巡り合えたら……\nとても素敵だと思いますね[ST:wait ]"
    },
    {
      "$id": 49,
      "label": "tev022701_MSG3001",
      "style": 1,
      "name": "あのデフィニアと繋がり　悪人達に\n武器や資金を渡していた　ジャスティンという\nコンパニオンがいたらしいですね[ST:wait ]"
    },
    {
      "$id": 50,
      "label": "tev022701_MSG3002",
      "style": 1,
      "name": "この星に来てから今まで\nおかしな事件が沢山起きましたけど……[ST:wait ]"
    },
    {
      "$id": 51,
      "label": "tev022701_MSG3003",
      "style": 1,
      "name": "もしかしたら　そのいくつかは\nそいつが裏で糸を引いていたのでしょうか？[ST:wait ]"
    },
    {
      "$id": 52,
      "label": "tev022701_MSG3004",
      "style": 1,
      "name": "今となっては真相は全て　闇の中ですが……[ST:wait ]"
    },
    {
      "$id": 53,
      "label": "tev022701_MSG3005",
      "style": 1,
      "name": "とにかく見つかって良かったですよ\n発見し　対処してくれたブレイドに\n感謝しなければなりませんね[ST:wait ]"
    }
  ]
}