{
  "schema": [
    {
      "name": "label",
      "type": 9
    },
    {
      "name": "style",
      "type": 2
    },
    {
      "name": "name",
      "type": 7
    }
  ],
  "rows": [
    {
      "$id": 1,
      "label": "tev035801_JNK0010",
      "style": 4,
      "name": "質問[ST:wait ]"
    },
    {
      "$id": 2,
      "label": "tev035801_SEL0011",
      "style": 3,
      "name": "仕事について聞く[ST:wait ]"
    },
    {
      "$id": 3,
      "label": "tev035801_JNK0020",
      "style": 4,
      "name": "興味[ST:wait ]"
    },
    {
      "$id": 4,
      "label": "tev035801_SEL0021",
      "style": 3,
      "name": "噂話を聞く[ST:wait ]"
    },
    {
      "$id": 5,
      "label": "tev035801_SEL0031",
      "style": 3,
      "name": "マ・ノン船について聞く"
    },
    {
      "$id": 6,
      "label": "tev035801_SEL0041",
      "style": 3,
      "name": "マ・ノン船について聞く"
    },
    {
      "$id": 7,
      "label": "tev035801_MSG0001",
      "style": 1,
      "name": "キラキラー　キラキラー\n今日もみんなビューティフルネ！[ST:wait ]"
    },
    {
      "$id": 8,
      "label": "tev035801_MSG0002",
      "style": 1,
      "name": "オー　あなた今　アタクシ一人で\nストレンジなこと言い出したって\n思ったデショ？[ST:wait ]"
    },
    {
      "$id": 9,
      "label": "tev035801_MSG0003",
      "style": 1,
      "name": "それなりに大切なお仕事なのヨ\nウフ　どんなお仕事かは\nそのうち教えてあげるワ[ST:wait ]"
    },
    {
      "$id": 10,
      "label": "tev035801_MSG0008",
      "style": 1,
      "name": "アタクシの娘のパニャルが\n地球人の服を　ベリー気に入ったのヨ[ST:wait ]"
    },
    {
      "$id": 11,
      "label": "tev035801_MSG0009",
      "style": 1,
      "name": "だけど　どれを着ても\nブカブカで　似合わないみたいでネ[ST:wait ]"
    },
    {
      "$id": 12,
      "label": "tev035801_MSG0010",
      "style": 1,
      "name": "どこかに似合うのがあるはずって\n商業エリアに入り浸り……\n元気にしてるカシラ？[ST:wait ]"
    },
    {
      "$id": 13,
      "label": "tev035801_MSG0015",
      "style": 1,
      "name": "フロアの真ん中に\nキラキラ光ってるモノ見えるカシラ？[ST:wait ]"
    },
    {
      "$id": 14,
      "label": "tev035801_MSG0016",
      "style": 1,
      "name": "アレが　マ・ノン船の\n重要なエネルギー源なのヨ[ST:wait ]"
    },
    {
      "$id": 15,
      "label": "tev035801_MSG0017",
      "style": 1,
      "name": "あそこから生まれるエネルギーを\n壁際の装置が変換してるの[ST:wait ]"
    },
    {
      "$id": 16,
      "label": "tev035801_MSG0018",
      "style": 1,
      "name": "ウフフフ　キラキラを紹介してあげたから\n喜んでるみたいだワ！[ST:wait ]"
    },
    {
      "$id": 17,
      "label": "tev035801_MSG0025",
      "style": 1,
      "name": "マ・ノン船のエネルギー源\nキラキラちゃんは　生きているのヨン[ST:wait ]"
    },
    {
      "$id": 18,
      "label": "tev035801_MSG0026",
      "style": 1,
      "name": "キラキラちゃんが喜ぶと発生するエネルギーを\n活用したのが　マ・ノン船ってワケ[ST:wait ]"
    },
    {
      "$id": 19,
      "label": "tev035801_MSG0027",
      "style": 1,
      "name": "地球人が使うどんなエネルギー源より\nパワフルでクリーンなの　すごいでしょ？[ST:wait ]"
    },
    {
      "$id": 20,
      "label": "tev035801_MSG0028",
      "style": 1,
      "name": "出会いは500光年離れた宙域で……[ST:wait ]"
    },
    {
      "$id": 21,
      "label": "tev035801_MSG0029",
      "style": 1,
      "name": "あら　キラキラちゃん　昔話は嫌いみたい\n不機嫌になっちゃうと困るから　ここまでネ[ST:wait ]"
    },
    {
      "$id": 22,
      "label": "tev035801_JNK0010",
      "style": 1,
      "name": ""
    },
    {
      "$id": 23,
      "label": "tev035801_SEL0011",
      "style": 1,
      "name": ""
    },
    {
      "$id": 24,
      "label": "tev035801_JNK0020",
      "style": 1,
      "name": ""
    },
    {
      "$id": 25,
      "label": "tev035801_SEL1021",
      "style": 3,
      "name": "最近の様子を尋ねる[ST:wait ]"
    },
    {
      "$id": 26,
      "label": "tev035801_MSG0011",
      "style": 1,
      "name": "パニャルの事　サンキューね！\nまともな仕事につけたみたいだし\n母はベリーハッピーネ！[ST:wait ]"
    },
    {
      "$id": 27,
      "label": "tev035801_MSG0012",
      "style": 1,
      "name": "サイズを調べたお礼にって\n香水っていうモノをもらったワ[ST:wait ]"
    },
    {
      "$id": 28,
      "label": "tev035801_MSG0013",
      "style": 1,
      "name": "あれ　とっても苦いのネ\nやっぱり美容と健康のためには\n辛い思いをしなきゃ……ン？[ST:wait ]"
    },
    {
      "$id": 29,
      "label": "tev035801_MSG0014",
      "style": 1,
      "name": "香水って飲みものじゃ無かったノ？\nオーマイガー！[ST:wait ]"
    }
  ]
}