{
  "schema": [
    {
      "name": "label",
      "type": 9
    },
    {
      "name": "style",
      "type": 2
    },
    {
      "name": "name",
      "type": 7
    }
  ],
  "rows": [
    {
      "$id": 1,
      "label": "xs05040100_MSG0001",
      "style": 0,
      "name": "実は　北の海岸地帯で原生生物が暴れていて\nアームズのチームが負傷したらしいんです[ST:wait ]"
    },
    {
      "$id": 2,
      "label": "xs05040100_MSG0002",
      "style": 0,
      "name": "それでその原生生物を排除しろ\nってことになりまして[ST:wait ]"
    },
    {
      "$id": 3,
      "label": "xs05040100_MSG0003",
      "style": 0,
      "name": "その準備をしてたところに　ヴァンダム司令\nからの任務まで飛び込んできちゃったんです[ST:wait ]"
    },
    {
      "$id": 4,
      "label": "xs05040100_MSG0004",
      "style": 0,
      "name": "まいりますよね\n僕達頼られまくっちゃって！[ST:wait ]"
    },
    {
      "$id": 5,
      "label": "xs05040100_MSG0005",
      "style": 0,
      "name": "それは大変ね[ST:wait ]"
    },
    {
      "$id": 6,
      "label": "xs05040100_MSG0006",
      "style": 0,
      "name": "分かったわ\nヴァンダムからの任務はこちらで引き受ける[ST:wait ]\n"
    },
    {
      "$id": 7,
      "label": "xs05040100_MSG0007",
      "style": 0,
      "name": "感謝します　大佐[ST:wait ]\n"
    },
    {
      "$id": 8,
      "label": "xs05040100_MSG0008",
      "style": 0,
      "name": "その任務なんですが\n忘却の渓谷のこの映像見てください[ST:wait ]"
    },
    {
      "$id": 9,
      "label": "xs05040100_MSG0009",
      "style": 0,
      "name": "望遠映像ね\nこれは宇宙船かしら[ST:wait ]"
    },
    {
      "$id": 10,
      "label": "xs05040100_MSG0010",
      "style": 0,
      "name": "比較物がないからサイズが\nわかりにくいですけど[ST:wait ]"
    },
    {
      "$id": 11,
      "label": "xs05040100_MSG0011",
      "style": 0,
      "name": "一方的に襲われてるような[ST:wide ]―[ST:wait ]"
    },
    {
      "$id": 12,
      "label": "xs05040100_MSG0012",
      "style": 0,
      "name": "タツの正義の心が燃え上がりますも！[ST:wait ]"
    },
    {
      "$id": 13,
      "label": "xs05040100_MSG0013",
      "style": 0,
      "name": "みなさん　助けにいってあげるですも！[ST:wait ]\n"
    },
    {
      "$id": 14,
      "label": "xs05040100_MSG0014",
      "style": 0,
      "name": "他人まかせの正義感を燃やすんじゃない！[ST:wait ]"
    },
    {
      "$id": 15,
      "label": "xs05040100_MSG0015",
      "style": 0,
      "name": "不鮮明だから確信は持てないけど\n襲っている方はグロウスの兵器に見える[ST:wait ]"
    },
    {
      "$id": 16,
      "label": "xs05040100_MSG0016",
      "style": 0,
      "name": "以前　交戦した機体に似ているわ[ST:wait ]"
    },
    {
      "$id": 17,
      "label": "xs05040100_MSG0017",
      "style": 0,
      "name": "そうなんです　それで現地に行って\n確認してくるというのが任務なんです[ST:wait ]"
    },
    {
      "$id": 18,
      "label": "xs05040100_MSG0018",
      "style": 0,
      "name": "未知の異星人の宇宙船だろうが\n敵の敵は味方だって[ST:wait ]\n"
    },
    {
      "$id": 19,
      "label": "xs05040100_MSG0019",
      "style": 0,
      "name": "ヴァンダムの親父が言ってました[ST:wait ]"
    },
    {
      "$id": 20,
      "label": "xs05040100_MSG0020",
      "style": 0,
      "name": "あたしも同感です[ST:wait ]"
    },
    {
      "$id": 21,
      "label": "xs05040100_MSG0021",
      "style": 0,
      "name": "この惑星に住む以上\n仲の良い隣人は多い方がいいですし[ST:wait ]"
    },
    {
      "$id": 22,
      "label": "xs05040100_MSG0022",
      "style": 0,
      "name": "その通りね[ST:wait ]\n"
    },
    {
      "$id": 23,
      "label": "xs05040100_MSG0023",
      "style": 0,
      "name": "状況は分かったわ\n後は任せて[ST:wait ]\n"
    },
    {
      "$id": 24,
      "label": "xs05040100_MSG0024",
      "style": 0,
      "name": "お願いします[ST:wait ]\n"
    }
  ]
}