{
  "schema": [
    {
      "name": "label",
      "type": 9
    },
    {
      "name": "style",
      "type": 2
    },
    {
      "name": "name",
      "type": 7
    }
  ],
  "rows": [
    {
      "$id": 1,
      "label": "xs32240100_MSG0010",
      "style": 0,
      "name": "おととい来やがれですも！[ST:wait ]"
    },
    {
      "$id": 2,
      "label": "xs32240100_MSG0020",
      "style": 0,
      "name": "タツはなんにもしてないじゃない！[ST:wait ]"
    },
    {
      "$id": 3,
      "label": "xs32240100_MSG0030",
      "style": 0,
      "name": "さっきの家の住人かは分からんが戻るか[ST:wait ]"
    },
    {
      "$id": 4,
      "label": "xs32240100_MSG0040",
      "style": 0,
      "name": "そうしましょう[ST:wait ]"
    }
  ]
}